czml3_ext/__init__.py
czml3_ext/definitions.py
czml3_ext/errors.py
czml3_ext/helpers.py
czml3_ext/packets.py
czml3_ext/rasters.py
czml3_ext/shapely_helpers.py
czml3_ext/data/__init__.py
czml3_ext/data/afghanistan.border
czml3_ext/data/cyprus.border
czml3_ext/data/djibouti.border
czml3_ext/data/egypt.border
czml3_ext/data/eritrea.border
czml3_ext/data/ethiopia.border
czml3_ext/data/f16.billboard
czml3_ext/data/f22.billboard
czml3_ext/data/gaza.border
czml3_ext/data/iran.border
czml3_ext/data/iraq.border
czml3_ext/data/israel.border
czml3_ext/data/israel_nowb.border
czml3_ext/data/jordan.border
czml3_ext/data/kuwait.border
czml3_ext/data/lebanon.border
czml3_ext/data/mig29.billboard
czml3_ext/data/missile.billboard
czml3_ext/data/oman.border
czml3_ext/data/pakistan.border
czml3_ext/data/qatar.border
czml3_ext/data/saudi_arabia.border
czml3_ext/data/small_boat.billboard
czml3_ext/data/somalia.border
czml3_ext/data/speed_boat.billboard
czml3_ext/data/sudan.border
czml3_ext/data/syria.border
czml3_ext/data/turkey.border
czml3_ext/data/turkmenistan.border
czml3_ext/data/uae.border
czml3_ext/data/west_bank.border
czml3_ext/data/yemen.border
saved_czmls/__init__.py
czml3_ext-0.11.0.dist-info/LICENSE.txt
czml3_ext-0.11.0.dist-info/METADATA
czml3_ext-0.11.0.dist-info/WHEEL
czml3_ext-0.11.0.dist-info/top_level.txt
czml3_ext-0.11.0.dist-info/RECORD
