Metadata-Version: 2.2
Name: czml3-ext
Version: 0.11.0
Summary: Create packets of CZML3
Author-email: Daniel Stoops <google@gmail.com>
License: BSD-3-Clause license
Project-URL: Homepage, https://github.com/Stoops-ML/czml3-ext
Project-URL: Repository, https://github.com/Stoops-ML/czml3-ext
Project-URL: Issues, https://github.com/Stoops-ML/czml3-ext/issues
Classifier: Intended Audience :: Science/Research
Classifier: Operating System :: OS Independent
Classifier: Programming Language :: Python
Classifier: Programming Language :: Python :: 3
Classifier: Programming Language :: Python :: 3.10
Classifier: Programming Language :: Python :: 3.11
Classifier: Programming Language :: Python :: 3.12
Classifier: Programming Language :: Python :: 3.13
Classifier: Programming Language :: Python :: Implementation :: CPython
Classifier: Topic :: Scientific/Engineering
Requires-Python: >=3.10
License-File: LICENSE.txt
Requires-Dist: numpy<3.0.0,>=1.0.0
Requires-Dist: shapely>=2.0.5
Requires-Dist: scikit-image>=0.24.0
Requires-Dist: czml3>=2.2.2
Requires-Dist: transforms84>=0.3.2
Requires-Dist: rasterio>=1.4.0
Provides-Extra: tests
Requires-Dist: ruff>=0.9.1; extra == "tests"
Requires-Dist: pytest>=8.2.2; extra == "tests"
Requires-Dist: mypy>=1.10.1; extra == "tests"
Requires-Dist: tox>=4.16.0; extra == "tests"
Requires-Dist: pytest-cov>=5.0.0; extra == "tests"
Provides-Extra: dev
Requires-Dist: ruff>=0.9.1; extra == "dev"
Requires-Dist: pytest>=8.2.2; extra == "dev"
Requires-Dist: mypy>=1.10.1; extra == "dev"
Requires-Dist: tox>=4.16.0; extra == "dev"
Requires-Dist: pytest-cov>=5.0.0; extra == "dev"
Requires-Dist: build; extra == "dev"
Provides-Extra: examples
Requires-Dist: marimo>=0.10.0; extra == "examples"
Requires-Dist: colourings>=0.2.0; extra == "examples"
